yzj/Bless.py
yzj/__init__.py
yzj-0.1.0.dist-info/LICENSE
yzj-0.1.0.dist-info/METADATA
yzj-0.1.0.dist-info/WHEEL
yzj-0.1.0.dist-info/top_level.txt
yzj-0.1.0.dist-info/RECORD
