Metadata-Version: 2.1
Name: yzj
Version: 0.1.0
Summary: A new be package
Home-page: UNKNOWN
Author: yzj
Author-email: youngzhanjie@qq.com
License: UNKNOWN
Platform: UNKNOWN
Classifier: Programming Language :: Python :: 3
Classifier: License :: OSI Approved :: MIT License
Classifier: Operating System :: OS Independent
License-File: LICENSE
